certus/__init__.py
certus/interface.py
certus/py.typed
certus/utils.py
certus/nodes/__init__.py
certus/nodes/core.py
certus/nodes/struct.py
certus/parsers/__init__.py
certus/parsers/struct.py
certus-0.0.2.dist-info/METADATA
certus-0.0.2.dist-info/WHEEL
certus-0.0.2.dist-info/licenses/LICENCE
certus-0.0.2.dist-info/RECORD
