Metadata-Version: 2.4
Name: certus
Version: 0.0.2
Summary: Confidence parsing of LLM outputs
Author-email: Henry Wilde <henrydavidwilde@gmail.com>
License: Copyright 2025 Henry Wilde
License-File: LICENCE
Requires-Python: >=3.12
Requires-Dist: google-genai>=1.33.0
